trytond/modules/calendar_todo/__init__.py
trytond/modules/calendar_todo/caldav.py
trytond/modules/calendar_todo/todo.py
trytond/modules/calendar_todo/todo.xml
trytond/modules/calendar_todo/tryton.cfg
trytond/modules/calendar_todo/webdav.py
trytond/modules/calendar_todo/locale/bg.po
trytond/modules/calendar_todo/locale/ca.po
trytond/modules/calendar_todo/locale/cs.po
trytond/modules/calendar_todo/locale/de.po
trytond/modules/calendar_todo/locale/es.po
trytond/modules/calendar_todo/locale/es_419.po
trytond/modules/calendar_todo/locale/fr.po
trytond/modules/calendar_todo/locale/hu_HU.po
trytond/modules/calendar_todo/locale/it_IT.po
trytond/modules/calendar_todo/locale/ja_JP.po
trytond/modules/calendar_todo/locale/lo.po
trytond/modules/calendar_todo/locale/lt.po
trytond/modules/calendar_todo/locale/nl.po
trytond/modules/calendar_todo/locale/pl.po
trytond/modules/calendar_todo/locale/pt_BR.po
trytond/modules/calendar_todo/locale/ru.po
trytond/modules/calendar_todo/locale/sl.po
trytond/modules/calendar_todo/locale/zh_CN.po
trytond/modules/calendar_todo/tests/__init__.py
trytond/modules/calendar_todo/tests/test_calendar_todo.py
trytond/modules/calendar_todo/view/attendee_form.xml
trytond/modules/calendar_todo/view/attendee_tree.xml
trytond/modules/calendar_todo/view/exdate_form.xml
trytond/modules/calendar_todo/view/exdate_tree.xml
trytond/modules/calendar_todo/view/exrule_form.xml
trytond/modules/calendar_todo/view/exrule_tree.xml
trytond/modules/calendar_todo/view/rdate_form.xml
trytond/modules/calendar_todo/view/rdate_tree.xml
trytond/modules/calendar_todo/view/rrule_form.xml
trytond/modules/calendar_todo/view/rrule_tree.xml
trytond/modules/calendar_todo/view/todo_form.xml
trytond/modules/calendar_todo/view/todo_tree.xml
trytond/modules/calendar_todo/view/todo_tree_occurence.xml
trytond_calendar_todo-4.2.0.dist-info/DESCRIPTION.rst
trytond_calendar_todo-4.2.0.dist-info/METADATA
trytond_calendar_todo-4.2.0.dist-info/RECORD
trytond_calendar_todo-4.2.0.dist-info/WHEEL
trytond_calendar_todo-4.2.0.dist-info/entry_points.txt
trytond_calendar_todo-4.2.0.dist-info/metadata.json
trytond_calendar_todo-4.2.0.dist-info/top_level.txt
